fastmicroservices/__init__.py
fastmicroservices/macroservice.py
fastmicroservices/microservice.py
fastmicroservices/templates.py
fastmicroservices-0.1.47.dist-info/LICENSE
fastmicroservices-0.1.47.dist-info/METADATA
fastmicroservices-0.1.47.dist-info/WHEEL
fastmicroservices-0.1.47.dist-info/RECORD
